tree_sitter_language_pack/__init__.py
tree_sitter_language_pack/py.typed
tree_sitter_language_pack/bindings/__init__.py
tree_sitter_language_pack/bindings/actionscript.pyd
tree_sitter_language_pack/bindings/ada.pyd
tree_sitter_language_pack/bindings/agda.pyd
tree_sitter_language_pack/bindings/apex.pyd
tree_sitter_language_pack/bindings/arduino.pyd
tree_sitter_language_pack/bindings/asm.pyd
tree_sitter_language_pack/bindings/astro.pyd
tree_sitter_language_pack/bindings/bash.pyd
tree_sitter_language_pack/bindings/beancount.pyd
tree_sitter_language_pack/bindings/bibtex.pyd
tree_sitter_language_pack/bindings/bicep.pyd
tree_sitter_language_pack/bindings/bitbake.pyd
tree_sitter_language_pack/bindings/bsl.pyd
tree_sitter_language_pack/bindings/c.pyd
tree_sitter_language_pack/bindings/cairo.pyd
tree_sitter_language_pack/bindings/capnp.pyd
tree_sitter_language_pack/bindings/chatito.pyd
tree_sitter_language_pack/bindings/clarity.pyd
tree_sitter_language_pack/bindings/clojure.pyd
tree_sitter_language_pack/bindings/cmake.pyd
tree_sitter_language_pack/bindings/comment.pyd
tree_sitter_language_pack/bindings/commonlisp.pyd
tree_sitter_language_pack/bindings/cpon.pyd
tree_sitter_language_pack/bindings/cpp.pyd
tree_sitter_language_pack/bindings/css.pyd
tree_sitter_language_pack/bindings/csv.pyd
tree_sitter_language_pack/bindings/cuda.pyd
tree_sitter_language_pack/bindings/d.pyd
tree_sitter_language_pack/bindings/dart.pyd
tree_sitter_language_pack/bindings/dockerfile.pyd
tree_sitter_language_pack/bindings/doxygen.pyd
tree_sitter_language_pack/bindings/dtd.pyd
tree_sitter_language_pack/bindings/elisp.pyd
tree_sitter_language_pack/bindings/elixir.pyd
tree_sitter_language_pack/bindings/elm.pyd
tree_sitter_language_pack/bindings/erlang.pyd
tree_sitter_language_pack/bindings/fennel.pyd
tree_sitter_language_pack/bindings/firrtl.pyd
tree_sitter_language_pack/bindings/fish.pyd
tree_sitter_language_pack/bindings/fortran.pyd
tree_sitter_language_pack/bindings/fsharp.pyd
tree_sitter_language_pack-0.11.0.dist-info/licenses/LICENSE
tree_sitter_language_pack-0.11.0.dist-info/METADATA
tree_sitter_language_pack-0.11.0.dist-info/WHEEL
tree_sitter_language_pack-0.11.0.dist-info/top_level.txt
tree_sitter_language_pack-0.11.0.dist-info/RECORD
