Metadata-Version: 2.4
Name: tree-sitter-language-pack
Version: 0.11.0
Summary: Comprehensive collection of 160+ tree-sitter language parsers
Author-email: Na'aman Hirschfeld <nhirschfeld@gmail.com>
License-Expression: MIT OR Apache-2.0
Project-URL: documentation, https://github.com/Goldziher/tree-sitter-language-pack#readme
Project-URL: homepage, https://github.com/Goldziher/tree-sitter-language-pack
Project-URL: issues, https://github.com/Goldziher/tree-sitter-language-pack/issues
Project-URL: repository, https://github.com/Goldziher/tree-sitter-language-pack
Keywords: ast,code,parser,parsing,syntax,text-processing,tree-sitter
Classifier: Development Status :: 5 - Production/Stable
Classifier: Intended Audience :: Developers
Classifier: Natural Language :: English
Classifier: Programming Language :: Python
Classifier: Programming Language :: Python :: 3 :: Only
Classifier: Programming Language :: Python :: 3.10
Classifier: Programming Language :: Python :: 3.11
Classifier: Programming Language :: Python :: 3.12
Classifier: Programming Language :: Python :: 3.13
Classifier: Programming Language :: Python :: 3.14
Classifier: Programming Language :: Python :: Implementation :: CPython
Classifier: Typing :: Typed
Requires-Python: >=3.10.0
License-File: LICENSE
Requires-Dist: tree-sitter>=0.25.2
Requires-Dist: tree-sitter-c-sharp>=0.23.1
Requires-Dist: tree-sitter-embedded-template>=0.25.0
Requires-Dist: tree-sitter-yaml>=0.7.2
Dynamic: license-file
